Workbook

Sheet Assumptions & Drivers
A1: 3-STATEMENT FINANCIAL MODEL
A2: ASSUMPTIONS & DRIVERS
A4: Scenario Selection: | B4: Base
A6: INPUTS (in $mm) | B6: 2021 | C6: 2022 | D6: 2023 | E6: 2024 | F6: 2025 | G6: 2026 | H6: 2027 | I6: 2028 | J6: 2029
A7: REVENUE ASSUMPTIONS
A8: Product Revenue | B8: 100 | C8: 110 | D8: 125 | E8: 140
A9: Service Revenue | B9: 50 | C9: 55 | D9: 62 | E9: 70
A10: Product Revenue Growth % | F10: =IF($B$4="Base",0.08,IF($B$4="Upside",0.12,0.05)) | G10: =IF($B$4="Base",0.06,IF($B$4="Upside",0.10,0.03)) | H10: =IF($B$4="Base",0.06,IF($B$4="Upside",0.10,0.03)) | I10: =IF($B$4="Base",0.06,IF($B$4="Upside",0.10,0.03)) | J10: =IF($B$4="Base",0.06,IF($B$4="Upside",0.10,0.03))
A11: Service Revenue Growth % | F11: =IF($B$4="Base",0.10,IF($B$4="Upside",0.15,0.07)) | G11: =IF($B$4="Base",0.08,IF($B$4="Upside",0.12,0.05)) | H11: =IF($B$4="Base",0.08,IF($B$4="Upside",0.12,0.05)) | I11: =IF($B$4="Base",0.08,IF($B$4="Upside",0.12,0.05)) | J11: =IF($B$4="Base",0.08,IF($B$4="Upside",0.12,0.05))
A13: OPERATING ASSUMPTIONS
A14: Gross Margin % | B14: 0.65 | C14: 0.65 | D14: 0.65 | E14: 0.65 | F14: =IF($B$4="Base",0.67,IF($B$4="Upside",0.70,0.64)) | G14: =IF($B$4="Base",0.67,IF($B$4="Upside",0.70,0.64)) | H14: =IF($B$4="Base",0.67,IF($B$4="Upside",0.70,0.64)) | I14: =IF($B$4="Base",0.67,IF($B$4="Upside",0.70,0.64)) | J14: =IF($B$4="Base",0.67,IF($B$4="Upside",0.70,0.64))
A15: SG&A % of Revenue | B15: 0.25 | C15: 0.25 | D15: 0.25 | E15: 0.25 | F15: =IF($B$4="Base",0.24,IF($B$4="Upside",0.23,0.26)) | G15: =IF($B$4="Base",0.24,IF($B$4="Upside",0.23,0.26)) | H15: =IF($B$4="Base",0.24,IF($B$4="Upside",0.23,0.26)) | I15: =IF($B$4="Base",0.24,IF($B$4="Upside",0.23,0.26)) | J15: =IF($B$4="Base",0.24,IF($B$4="Upside",0.23,0.26))
A16: R&D % of Revenue | B16: 0.12 | C16: 0.12 | D16: 0.12 | E16: 0.12 | F16: =IF($B$4="Base",0.12,IF($B$4="Upside",0.13,0.10)) | G16: =IF($B$4="Base",0.12,IF($B$4="Upside",0.13,0.10)) | H16: =IF($B$4="Base",0.12,IF($B$4="Upside",0.13,0.10)) | I16: =IF($B$4="Base",0.12,IF($B$4="Upside",0.13,0.10)) | J16: =IF($B$4="Base",0.12,IF($B$4="Upside",0.13,0.10))
A17: D&A % of Revenue | B17: 0.05 | C17: 0.05 | D17: 0.05 | E17: 0.05 | F17: 0.05 | G17: 0.05 | H17: 0.05 | I17: 0.05 | J17: 0.05
A18: Tax Rate | B18: 0.25 | C18: 0.25 | D18: 0.25 | E18: 0.25 | F18: 0.25 | G18: 0.25 | H18: 0.25 | I18: 0.25 | J18: 0.25
A20: BALANCE SHEET ASSUMPTIONS
A21: AR Days | B21: 45 | C21: 45 | D21: 45 | E21: 45 | F21: 45 | G21: 45 | H21: 45 | I21: 45 | J21: 45
A22: Inventory Days | B22: 60 | C22: 60 | D22: 60 | E22: 60 | F22: 60 | G22: 60 | H22: 60 | I22: 60 | J22: 60
A23: AP Days | B23: 30 | C23: 30 | D23: 30 | E23: 30 | F23: 30 | G23: 30 | H23: 30 | I23: 30 | J23: 30
A24: Other Current Assets % of Rev | B24: 0.03 | C24: 0.03 | D24: 0.03 | E24: 0.03 | F24: 0.03 | G24: 0.03 | H24: 0.03 | I24: 0.03 | J24: 0.03
A25: Other Current Liab % of Rev | B25: 0.02 | C25: 0.02 | D25: 0.02 | E25: 0.02 | F25: 0.02 | G25: 0.02 | H25: 0.02 | I25: 0.02 | J25: 0.02
A26: CapEx % of Revenue | B26: 0.08 | C26: 0.08 | D26: 0.08 | E26: 0.08 | F26: =IF($B$4="Base",0.07,IF($B$4="Upside",0.09,0.06)) | G26: =IF($B$4="Base",0.07,IF($B$4="Upside",0.09,0.06)) | H26: =IF($B$4="Base",0.07,IF($B$4="Upside",0.09,0.06)) | I26: =IF($B$4="Base",0.07,IF($B$4="Upside",0.09,0.06)) | J26: =IF($B$4="Base",0.07,IF($B$4="Upside",0.09,0.06))
A28: DEBT ASSUMPTIONS
A29: Beginning Debt (2021) | B29: 50
A30: Revolver Interest Rate | B30: 0.05 | C30: 0.05 | D30: 0.05 | E30: 0.05 | F30: 0.05 | G30: 0.05 | H30: 0.05 | I30: 0.05 | J30: 0.05
A31: Beginning Equity (2021) | B31: 200
A32: Beginning Cash (2021) | B32: 30
A33: Beginning PP&E (2021) | B33: 80

Sheet Income Statement
A1: INCOME STATEMENT
A2: ($ in millions)
A4: Period | B4: 2021 | C4: 2022 | D4: 2023 | E4: 2024 | F4: 2025 | G4: 2026 | H4: 2027 | I4: 2028 | J4: 2029
A5: Revenue
A6: Product Revenue | B6: ='Assumptions & Drivers'!B8 | C6: ='Assumptions & Drivers'!C8 | D6: ='Assumptions & Drivers'!D8 | E6: ='Assumptions & Drivers'!E8 | F6: =E6*(1+'Assumptions & Drivers'!F10) | G6: =F6*(1+'Assumptions & Drivers'!G10) | H6: =G6*(1+'Assumptions & Drivers'!H10) | I6: =H6*(1+'Assumptions & Drivers'!I10) | J6: =I6*(1+'Assumptions & Drivers'!J10)
A7: Service Revenue | B7: ='Assumptions & Drivers'!B9 | C7: ='Assumptions & Drivers'!C9 | D7: ='Assumptions & Drivers'!D9 | E7: ='Assumptions & Drivers'!E9 | F7: =E7*(1+'Assumptions & Drivers'!F11) | G7: =F7*(1+'Assumptions & Drivers'!G11) | H7: =G7*(1+'Assumptions & Drivers'!H11) | I7: =H7*(1+'Assumptions & Drivers'!I11) | J7: =I7*(1+'Assumptions & Drivers'!J11)
A8: Total Revenue | B8: =SUM(B6:B7) | C8: =SUM(C6:C7) | D8: =SUM(D6:D7) | E8: =SUM(E6:E7) | F8: =SUM(F6:F7) | G8: =SUM(G6:G7) | H8: =SUM(H6:H7) | I8: =SUM(I6:I7) | J8: =SUM(J6:J7)
A9: Cost of Goods Sold | B9: =B8*(1-'Assumptions & Drivers'!B14) | C9: =C8*(1-'Assumptions & Drivers'!C14) | D9: =D8*(1-'Assumptions & Drivers'!D14) | E9: =E8*(1-'Assumptions & Drivers'!E14) | F9: =F8*(1-'Assumptions & Drivers'!F14) | G9: =G8*(1-'Assumptions & Drivers'!G14) | H9: =H8*(1-'Assumptions & Drivers'!H14) | I9: =I8*(1-'Assumptions & Drivers'!I14) | J9: =J8*(1-'Assumptions & Drivers'!J14)
A10: Gross Profit | B10: =B8-B9 | C10: =C8-C9 | D10: =D8-D9 | E10: =E8-E9 | F10: =F8-F9 | G10: =G8-G9 | H10: =H8-H9 | I10: =I8-I9 | J10: =J8-J9
A11: Operating Expenses
A12: SG&A | B12: =B8*'Assumptions & Drivers'!B15 | C12: =C8*'Assumptions & Drivers'!C15 | D12: =D8*'Assumptions & Drivers'!D15 | E12: =E8*'Assumptions & Drivers'!E15 | F12: =F8*'Assumptions & Drivers'!F15 | G12: =G8*'Assumptions & Drivers'!G15 | H12: =H8*'Assumptions & Drivers'!H15 | I12: =I8*'Assumptions & Drivers'!I15 | J12: =J8*'Assumptions & Drivers'!J15
A13: R&D | B13: =B8*'Assumptions & Drivers'!B16 | C13: =C8*'Assumptions & Drivers'!C16 | D13: =D8*'Assumptions & Drivers'!D16 | E13: =E8*'Assumptions & Drivers'!E16 | F13: =F8*'Assumptions & Drivers'!F16 | G13: =G8*'Assumptions & Drivers'!G16 | H13: =H8*'Assumptions & Drivers'!H16 | I13: =I8*'Assumptions & Drivers'!I16 | J13: =J8*'Assumptions & Drivers'!J16
A14: D&A | B14: =B8*'Assumptions & Drivers'!B17 | C14: =C8*'Assumptions & Drivers'!C17 | D14: =D8*'Assumptions & Drivers'!D17 | E14: =E8*'Assumptions & Drivers'!E17 | F14: =F8*'Assumptions & Drivers'!F17 | G14: =G8*'Assumptions & Drivers'!G17 | H14: =H8*'Assumptions & Drivers'!H17 | I14: =I8*'Assumptions & Drivers'!I17 | J14: =J8*'Assumptions & Drivers'!J17
A15: Total Operating Expenses | B15: =SUM(B12:B14) | C15: =SUM(C12:C14) | D15: =SUM(D12:D14) | E15: =SUM(E12:E14) | F15: =SUM(F12:F14) | G15: =SUM(G12:G14) | H15: =SUM(H12:H14) | I15: =SUM(I12:I14) | J15: =SUM(J12:J14)
A16: EBIT | B16: =B10-B15 | C16: =C10-C15 | D16: =D10-D15 | E16: =E10-E15 | F16: =F10-F15 | G16: =G10-G15 | H16: =H10-H15 | I16: =I10-I15 | J16: =J10-J15
A17: Interest Expense | B17: ='Balance Sheet'!B26*'Assumptions & Drivers'!B31 | C17: ='Balance Sheet'!C26*'Assumptions & Drivers'!C31 | D17: ='Balance Sheet'!D26*'Assumptions & Drivers'!D31 | E17: ='Balance Sheet'!E26*'Assumptions & Drivers'!E31 | F17: ='Balance Sheet'!F26*'Assumptions & Drivers'!F31 | G17: ='Balance Sheet'!G26*'Assumptions & Drivers'!G31 | H17: ='Balance Sheet'!H26*'Assumptions & Drivers'!H31 | I17: ='Balance Sheet'!I26*'Assumptions & Drivers'!I31 | J17: ='Balance Sheet'!J26*'Assumptions & Drivers'!J31
A18: EBT | B18: =B16-B17 | C18: =C16-C17 | D18: =D16-D17 | E18: =E16-E17 | F18: =F16-F17 | G18: =G16-G17 | H18: =H16-H17 | I18: =I16-I17 | J18: =J16-J17
A19: Taxes | B19: =B18*'Assumptions & Drivers'!B18 | C19: =C18*'Assumptions & Drivers'!C18 | D19: =D18*'Assumptions & Drivers'!D18 | E19: =E18*'Assumptions & Drivers'!E18 | F19: =F18*'Assumptions & Drivers'!F18 | G19: =G18*'Assumptions & Drivers'!G18 | H19: =H18*'Assumptions & Drivers'!H18 | I19: =I18*'Assumptions & Drivers'!I18 | J19: =J18*'Assumptions & Drivers'!J18
A20: Net Income | B20: =B18-B19 | C20: =C18-C19 | D20: =D18-D19 | E20: =E18-E19 | F20: =F18-F19 | G20: =G18-G19 | H20: =H18-H19 | I20: =I18-I19 | J20: =J18-J19
A22: KEY METRICS
A23: EBITDA | B23: =B16+B14 | C23: =C16+C14 | D23: =D16+D14 | E23: =E16+E14 | F23: =F16+F14 | G23: =G16+G14 | H23: =H16+H14 | I23: =I16+I14 | J23: =J16+J14
A24: EBITDA Margin | B24: =B23/B8 | C24: =C23/C8 | D24: =D23/D8 | E24: =E23/E8 | F24: =F23/F8 | G24: =G23/G8 | H24: =H23/H8 | I24: =I23/I8 | J24: =J23/J8
A25: Net Income Margin | B25: =B20/B8 | C25: =C20/C8 | D25: =D20/D8 | E25: =E20/E8 | F25: =F20/F8 | G25: =G20/G8 | H25: =H20/H8 | I25: =I20/I8 | J25: =J20/J8

Sheet Balance Sheet
A1: BALANCE SHEET
A2: ($ in millions)
A4: Period Ending | B4: 2021 | C4: 2022 | D4: 2023 | E4: 2024 | F4: 2025 | G4: 2026 | H4: 2027 | I4: 2028 | J4: 2029
A5: ASSETS
A6: Current Assets
A7: Cash | B7: ='Assumptions & Drivers'!B33 | C7: ='Cash Flow'!C32 | D7: ='Cash Flow'!D32 | E7: ='Cash Flow'!E32 | F7: ='Cash Flow'!F32 | G7: ='Cash Flow'!G32 | H7: ='Cash Flow'!H32 | I7: ='Cash Flow'!I32 | J7: ='Cash Flow'!J32
A8: Accounts Receivable | B8: ='Income Statement'!B7*'Assumptions & Drivers'!B21/365 | C8: ='Income Statement'!C7*'Assumptions & Drivers'!C21/365 | D8: ='Income Statement'!D7*'Assumptions & Drivers'!D21/365 | E8: ='Income Statement'!E7*'Assumptions & Drivers'!E21/365 | F8: ='Income Statement'!F7*'Assumptions & Drivers'!F21/365 | G8: ='Income Statement'!G7*'Assumptions & Drivers'!G21/365 | H8: ='Income Statement'!H7*'Assumptions & Drivers'!H21/365 | I8: ='Income Statement'!I7*'Assumptions & Drivers'!I21/365 | J8: ='Income Statement'!J7*'Assumptions & Drivers'!J21/365
A9: Inventory | B9: ='Income Statement'!B8*'Assumptions & Drivers'!B22/365 | C9: ='Income Statement'!C8*'Assumptions & Drivers'!C22/365 | D9: ='Income Statement'!D8*'Assumptions & Drivers'!D22/365 | E9: ='Income Statement'!E8*'Assumptions & Drivers'!E22/365 | F9: ='Income Statement'!F8*'Assumptions & Drivers'!F22/365 | G9: ='Income Statement'!G8*'Assumptions & Drivers'!G22/365 | H9: ='Income Statement'!H8*'Assumptions & Drivers'!H22/365 | I9: ='Income Statement'!I8*'Assumptions & Drivers'!I22/365 | J9: ='Income Statement'!J8*'Assumptions & Drivers'!J22/365
A10: Other Current Assets | B10: ='Income Statement'!B7*'Assumptions & Drivers'!B24 | C10: ='Income Statement'!C7*'Assumptions & Drivers'!C24 | D10: ='Income Statement'!D7*'Assumptions & Drivers'!D24 | E10: ='Income Statement'!E7*'Assumptions & Drivers'!E24 | F10: ='Income Statement'!F7*'Assumptions & Drivers'!F24 | G10: ='Income Statement'!G7*'Assumptions & Drivers'!G24 | H10: ='Income Statement'!H7*'Assumptions & Drivers'!H24 | I10: ='Income Statement'!I7*'Assumptions & Drivers'!I24 | J10: ='Income Statement'!J7*'Assumptions & Drivers'!J24
A11: Total Current Assets | B11: =SUM(B7:B10) | C11: =SUM(C7:C10) | D11: =SUM(D7:D10) | E11: =SUM(E7:E10) | F11: =SUM(F7:F10) | G11: =SUM(G7:G10) | H11: =SUM(H7:H10) | I11: =SUM(I7:I10) | J11: =SUM(J7:J10)
A12: PP&E, Net | B12: ='Assumptions & Drivers'!B34 | C12: =B12+'Cash Flow'!C18-'Income Statement'!C13 | D12: =C12+'Cash Flow'!D18-'Income Statement'!D13 | E12: =D12+'Cash Flow'!E18-'Income Statement'!E13 | F12: =E12+'Cash Flow'!F18-'Income Statement'!F13 | G12: =F12+'Cash Flow'!G18-'Income Statement'!G13 | H12: =G12+'Cash Flow'!H18-'Income Statement'!H13 | I12: =H12+'Cash Flow'!I18-'Income Statement'!I13 | J12: =I12+'Cash Flow'!J18-'Income Statement'!J13
A13: Total Assets | B13: =B11+B12 | C13: =C11+C12 | D13: =D11+D12 | E13: =E11+E12 | F13: =F11+F12 | G13: =G11+G12 | H13: =H11+H12 | I13: =I11+I12 | J13: =J11+J12
A15: LIABILITIES & EQUITY
A16: Current Liabilities
A17: Accounts Payable | B17: ='Income Statement'!B8*'Assumptions & Drivers'!B23/365 | C17: ='Income Statement'!C8*'Assumptions & Drivers'!C23/365 | D17: ='Income Statement'!D8*'Assumptions & Drivers'!D23/365 | E17: ='Income Statement'!E8*'Assumptions & Drivers'!E23/365 | F17: ='Income Statement'!F8*'Assumptions & Drivers'!F23/365 | G17: ='Income Statement'!G8*'Assumptions & Drivers'!G23/365 | H17: ='Income Statement'!H8*'Assumptions & Drivers'!H23/365 | I17: ='Income Statement'!I8*'Assumptions & Drivers'!I23/365 | J17: ='Income Statement'!J8*'Assumptions & Drivers'!J23/365
A18: Other Current Liabilities | B18: ='Income Statement'!B7*'Assumptions & Drivers'!B25 | C18: ='Income Statement'!C7*'Assumptions & Drivers'!C25 | D18: ='Income Statement'!D7*'Assumptions & Drivers'!D25 | E18: ='Income Statement'!E7*'Assumptions & Drivers'!E25 | F18: ='Income Statement'!F7*'Assumptions & Drivers'!F25 | G18: ='Income Statement'!G7*'Assumptions & Drivers'!G25 | H18: ='Income Statement'!H7*'Assumptions & Drivers'!H25 | I18: ='Income Statement'!I7*'Assumptions & Drivers'!I25 | J18: ='Income Statement'!J7*'Assumptions & Drivers'!J25
A19: Total Current Liabilities | B19: =SUM(B17:B18) | C19: =SUM(C17:C18) | D19: =SUM(D17:D18) | E19: =SUM(E17:E18) | F19: =SUM(F17:F18) | G19: =SUM(G17:G18) | H19: =SUM(H17:H18) | I19: =SUM(I17:I18) | J19: =SUM(J17:J18)
A20: Revolver / Debt | B20: ='Assumptions & Drivers'!B30 | C20: ='Cash Flow'!C30 | D20: ='Cash Flow'!D30 | E20: ='Cash Flow'!E30 | F20: ='Cash Flow'!F30 | G20: ='Cash Flow'!G30 | H20: ='Cash Flow'!H30 | I20: ='Cash Flow'!I30 | J20: ='Cash Flow'!J30
A21: Total Liabilities | B21: =B19+B20 | C21: =C19+C20 | D21: =D19+D20 | E21: =E19+E20 | F21: =F19+F20 | G21: =G19+G20 | H21: =H19+H20 | I21: =I19+I20 | J21: =J19+J20
A22: Shareholders' Equity | B22: ='Assumptions & Drivers'!B32 | C22: =B22+'Income Statement'!C19 | D22: =C22+'Income Statement'!D19 | E22: =D22+'Income Statement'!E19 | F22: =E22+'Income Statement'!F19 | G22: =F22+'Income Statement'!G19 | H22: =G22+'Income Statement'!H19 | I22: =H22+'Income Statement'!I19 | J22: =I22+'Income Statement'!J19
A23: Total Liabilities & Equity | B23: =B21+B22 | C23: =C21+C22 | D23: =D21+D22 | E23: =E21+E22 | F23: =F21+F22 | G23: =G21+G22 | H23: =H21+H22 | I23: =I21+I22 | J23: =J21+J22
A25: Balance Check | B25: =B13-B23 | C25: =C13-C23 | D25: =D13-D23 | E25: =E13-E23 | F25: =F13-F23 | G25: =G13-G23 | H25: =H13-H23 | I25: =I13-I23 | J25: =J13-J23

Sheet Cash Flow
A1: CASH FLOW STATEMENT
A2: ($ in millions)
A4: Period | B4: 2021 | C4: 2022 | D4: 2023 | E4: 2024 | F4: 2025 | G4: 2026 | H4: 2027 | I4: 2028 | J4: 2029
A5: OPERATING ACTIVITIES
A6: Net Income | B6: ='Income Statement'!B19 | C6: ='Income Statement'!C19 | D6: ='Income Statement'!D19 | E6: ='Income Statement'!E19 | F6: ='Income Statement'!F19 | G6: ='Income Statement'!G19 | H6: ='Income Statement'!H19 | I6: ='Income Statement'!I19 | J6: ='Income Statement'!J19
A7: D&A | B7: ='Income Statement'!B13 | C7: ='Income Statement'!C13 | D7: ='Income Statement'!D13 | E7: ='Income Statement'!E13 | F7: ='Income Statement'!F13 | G7: ='Income Statement'!G13 | H7: ='Income Statement'!H13 | I7: ='Income Statement'!I13 | J7: ='Income Statement'!J13
A8: Changes in Working Capital:
A9: Change in AR | B9: 0 | C9: =-('Balance Sheet'!C8-'Balance Sheet'!B8) | D9: =-('Balance Sheet'!D8-'Balance Sheet'!C8) | E9: =-('Balance Sheet'!E8-'Balance Sheet'!D8) | F9: =-('Balance Sheet'!F8-'Balance Sheet'!E8) | G9: =-('Balance Sheet'!G8-'Balance Sheet'!F8) | H9: =-('Balance Sheet'!H8-'Balance Sheet'!G8) | I9: =-('Balance Sheet'!I8-'Balance Sheet'!H8) | J9: =-('Balance Sheet'!J8-'Balance Sheet'!I8)
A10: Change in Inventory | B10: 0 | C10: =-('Balance Sheet'!C9-'Balance Sheet'!B9) | D10: =-('Balance Sheet'!D9-'Balance Sheet'!C9) | E10: =-('Balance Sheet'!E9-'Balance Sheet'!D9) | F10: =-('Balance Sheet'!F9-'Balance Sheet'!E9) | G10: =-('Balance Sheet'!G9-'Balance Sheet'!F9) | H10: =-('Balance Sheet'!H9-'Balance Sheet'!G9) | I10: =-('Balance Sheet'!I9-'Balance Sheet'!H9) | J10: =-('Balance Sheet'!J9-'Balance Sheet'!I9)
A11: Change in Other Current Assets | B11: 0 | C11: =-('Balance Sheet'!C10-'Balance Sheet'!B10) | D11: =-('Balance Sheet'!D10-'Balance Sheet'!C10) | E11: =-('Balance Sheet'!E10-'Balance Sheet'!D10) | F11: =-('Balance Sheet'!F10-'Balance Sheet'!E10) | G11: =-('Balance Sheet'!G10-'Balance Sheet'!F10) | H11: =-('Balance Sheet'!H10-'Balance Sheet'!G10) | I11: =-('Balance Sheet'!I10-'Balance Sheet'!H10) | J11: =-('Balance Sheet'!J10-'Balance Sheet'!I10)
A12: Change in AP | B12: 0 | C12: ='Balance Sheet'!C19-'Balance Sheet'!B19 | D12: ='Balance Sheet'!D19-'Balance Sheet'!C19 | E12: ='Balance Sheet'!E19-'Balance Sheet'!D19 | F12: ='Balance Sheet'!F19-'Balance Sheet'!E19 | G12: ='Balance Sheet'!G19-'Balance Sheet'!F19 | H12: ='Balance Sheet'!H19-'Balance Sheet'!G19 | I12: ='Balance Sheet'!I19-'Balance Sheet'!H19 | J12: ='Balance Sheet'!J19-'Balance Sheet'!I19
A13: Change in Other Current Liab | B13: 0 | C13: ='Balance Sheet'!C20-'Balance Sheet'!B20 | D13: ='Balance Sheet'!D20-'Balance Sheet'!C20 | E13: ='Balance Sheet'!E20-'Balance Sheet'!D20 | F13: ='Balance Sheet'!F20-'Balance Sheet'!E20 | G13: ='Balance Sheet'!G20-'Balance Sheet'!F20 | H13: ='Balance Sheet'!H20-'Balance Sheet'!G20 | I13: ='Balance Sheet'!I20-'Balance Sheet'!H20 | J13: ='Balance Sheet'!J20-'Balance Sheet'!I20
A14: Cash from Operations | B14: =SUM(B6:B13) | C14: =SUM(C6:C13) | D14: =SUM(D6:D13) | E14: =SUM(E6:E13) | F14: =SUM(F6:F13) | G14: =SUM(G6:G13) | H14: =SUM(H6:H13) | I14: =SUM(I6:I13) | J14: =SUM(J6:J13)
A16: INVESTING ACTIVITIES
A17: CapEx | B17: =-('Income Statement'!B7*'Assumptions & Drivers'!B26) | C17: =-('Income Statement'!C7*'Assumptions & Drivers'!C26) | D17: =-('Income Statement'!D7*'Assumptions & Drivers'!D26) | E17: =-('Income Statement'!E7*'Assumptions & Drivers'!E26) | F17: =-('Income Statement'!F7*'Assumptions & Drivers'!F26) | G17: =-('Income Statement'!G7*'Assumptions & Drivers'!G26) | H17: =-('Income Statement'!H7*'Assumptions & Drivers'!H26) | I17: =-('Income Statement'!I7*'Assumptions & Drivers'!I26) | J17: =-('Income Statement'!J7*'Assumptions & Drivers'!J26)
A18: Cash from Investing | B18: =B17 | C18: =C17 | D18: =D17 | E18: =E17 | F18: =F17 | G18: =G17 | H18: =H17 | I18: =I17 | J18: =J17
A20: FINANCING ACTIVITIES
A21: Net Borrowing / (Repayment) | B21: 0 | C21: ='Balance Sheet'!C26-'Balance Sheet'!B26 | D21: ='Balance Sheet'!D26-'Balance Sheet'!C26 | E21: ='Balance Sheet'!E26-'Balance Sheet'!D26 | F21: ='Balance Sheet'!F26-'Balance Sheet'!E26 | G21: ='Balance Sheet'!G26-'Balance Sheet'!F26 | H21: ='Balance Sheet'!H26-'Balance Sheet'!G26 | I21: ='Balance Sheet'!I26-'Balance Sheet'!H26 | J21: ='Balance Sheet'!J26-'Balance Sheet'!I26
A22: Cash from Financing | B22: =B21 | C22: =C21 | D22: =D21 | E22: =E21 | F22: =F21 | G22: =G21 | H22: =H21 | I22: =I21 | J22: =J21
A24: Net Change in Cash | B24: =B14+B18+B22 | C24: =C14+C18+C22 | D24: =D14+D18+D22 | E24: =E14+E18+E22 | F24: =F14+F18+F22 | G24: =G14+G18+G22 | H24: =H14+H18+H22 | I24: =I14+I18+I22 | J24: =J14+J18+J22
A25: Beginning Cash | B25: ='Assumptions & Drivers'!B33 | C25: =B26 | D25: =C26 | E25: =D26 | F25: =E26 | G25: =F26 | H25: =G26 | I25: =H26 | J25: =I26
A26: Ending Cash (before revolver) | B26: =B25+B24 | C26: =C25+C24 | D26: =D25+D24 | E26: =E25+E24 | F26: =F25+F24 | G26: =G25+G24 | H26: =H25+H24 | I26: =I25+I24 | J26: =J25+J24
A28: REVOLVER LOGIC
A29: Beginning Debt | B29: ='Assumptions & Drivers'!B30 | C29: =B30 | D29: =C30 | E29: =D30 | F29: =E30 | G29: =F30 | H29: =G30 | I29: =H30 | J29: =I30
A30: Ending Debt | B30: =MAX(0,B29-B26) | C30: =MAX(0,C29-C26) | D30: =MAX(0,D29-D26) | E30: =MAX(0,E29-E26) | F30: =MAX(0,F29-F26) | G30: =MAX(0,G29-G26) | H30: =MAX(0,H29-H26) | I30: =MAX(0,I29-I26) | J30: =MAX(0,J29-J26)
A31: Ending Cash | B31: =B26+B29-B30 | C31: =C26+C29-C30 | D31: =D26+D29-D30 | E31: =E26+E29-E30 | F31: =F26+F29-F30 | G31: =G26+G29-G30 | H31: =H26+H29-H30 | I31: =I26+I29-I30 | J31: =J26+J29-J30
A33: KEY METRICS
A34: Free Cash Flow | B34: =B14+B17 | C34: =C14+C17 | D34: =D14+D17 | E34: =E14+E17 | F34: =F14+F17 | G34: =G14+G17 | H34: =H14+H17 | I34: =I14+I17 | J34: =J14+J17

Sheet Charts
A1: KEY CHARTS & VISUALIZATIONS
A3: Year | B3: Revenue | C3: EBITDA | D3: Free Cash Flow
A4: 2021 | B4: ='Income Statement'!B7 | C4: ='Income Statement'!B22 | D4: ='Cash Flow'!B36
A5: 2022 | B5: ='Income Statement'!C7 | C5: ='Income Statement'!C22 | D5: ='Cash Flow'!C36
A6: 2023 | B6: ='Income Statement'!D7 | C6: ='Income Statement'!D22 | D6: ='Cash Flow'!D36
A7: 2024 | B7: ='Income Statement'!E7 | C7: ='Income Statement'!E22 | D7: ='Cash Flow'!E36
A8: 2025 | B8: ='Income Statement'!F7 | C8: ='Income Statement'!F22 | D8: ='Cash Flow'!F36
A9: 2026 | B9: ='Income Statement'!G7 | C9: ='Income Statement'!G22 | D9: ='Cash Flow'!G36
A10: 2027 | B10: ='Income Statement'!H7 | C10: ='Income Statement'!H22 | D10: ='Cash Flow'!H36
A11: 2028 | B11: ='Income Statement'!I7 | C11: ='Income Statement'!I22 | D11: ='Cash Flow'!I36
A12: 2029 | B12: ='Income Statement'!J7 | C12: ='Income Statement'!J22 | D12: ='Cash Flow'!J36
